PySparkAudit/PySparkAudit.py
PySparkAudit/__init__.py
PySparkAudit/basics.py
PySparkAudit-1.0.0.dist-info/DESCRIPTION.rst
PySparkAudit-1.0.0.dist-info/METADATA
PySparkAudit-1.0.0.dist-info/RECORD
PySparkAudit-1.0.0.dist-info/WHEEL
PySparkAudit-1.0.0.dist-info/metadata.json
PySparkAudit-1.0.0.dist-info/top_level.txt
