Metadata-Version: 2.0
Name: PySparkAudit
Version: 1.0.0
Summary: PySpark Data Audit library
Home-page: https://github.com/runawayhorse001/PySparkAudit.git
Author: Wenqiang Feng and Ximing Xu
Author-email: von198@gmail.com
License: MIT
Platform: UNKNOWN
Classifier: Development Status :: 2 - Pre-Alpha
Classifier: Framework :: IPython
Classifier: Framework :: Jupyter
Classifier: Environment :: Console
Classifier: Environment :: MacOS X
Classifier: Operating System :: MacOS
Classifier: License :: OSI Approved :: MIT License
Classifier: Intended Audience :: Developers
Classifier: Programming Language :: Python
Classifier: Programming Language :: Python :: 2
Classifier: Programming Language :: Python :: 3
Requires-Dist: matplotlib
Requires-Dist: numpy
Requires-Dist: pandas
Requires-Dist: seaborn
Requires-Dist: xlsxwriter
